MANIFEST.in
setup.cfg
setup.py
pyschemes/__init__.py
pyschemes/base.py
pyschemes/validators.py
pyschemes.egg-info/PKG-INFO
pyschemes.egg-info/SOURCES.txt
pyschemes.egg-info/dependency_links.txt
pyschemes.egg-info/top_level.txt