Metadata-Version: 1.0
Name: pyschemes
Version: 1.0.0
Summary: A Pythonic data-structure validator
Home-page: https://github.com/shivylp/pyschemes
Author: Shivaprasad
Author-email: shiv.ylp@gmail.com
License: MIT
Keywords: validator schema
Platform: UNKNOWN
